py_setenv
