Metadata-Version: 2.1
Name: py-setenv
Version: 1.1.0
Summary: CLI App to manage window environment variables
Home-page: https://github.com/beliaev-maksim/py_setenv
Author: Maksim Beliaev
Author-email: beliaev.m.s@gmail.com
License: MIT
Download-URL: https://github.com/beliaev-maksim/py_setenv/archive/v1.1.tar.gz
Keywords: CLI,Environment,Variable
Platform: UNKNOWN
Classifier: Development Status :: 5 - Production/Stable
Classifier: Intended Audience :: Developers
Classifier: Topic :: Software Development :: Build Tools
Classifier: License :: OSI Approved :: MIT License
Classifier: Programming Language :: Python :: 3.4
Classifier: Programming Language :: Python :: 3.5
Classifier: Programming Language :: Python :: 3.6
Classifier: Programming Language :: Python :: 3.7
Classifier: Programming Language :: Python :: 3.8
Classifier: Programming Language :: Python :: 3.9
